matrix_asgi/__init__.py
matrix_asgi/__main__.py
matrix_asgi/conf.py
matrix_asgi/consumers.py
matrix_asgi/server.py
matrix_asgi/utils.py
matrix_asgi-2.0.0.dist-info/METADATA
matrix_asgi-2.0.0.dist-info/entry_points.txt
matrix_asgi-2.0.0.dist-info/WHEEL
matrix_asgi-2.0.0.dist-info/RECORD
