Metadata-Version: 2.1
Name: matrix-asgi
Version: 2.0.0
Summary: ASGI Server for the Matrix protocol
Home-page: https://github.com/nim65s/matrix-asgi
License: BSD-2-Clause
Author: Guilhem Saurel
Author-email: guilhem.saurel@laas.fr
Requires-Python: >=3.9,<4.0
Classifier: License :: OSI Approved :: BSD License
Classifier: Programming Language :: Python :: 3
Classifier: Programming Language :: Python :: 3.9
Classifier: Programming Language :: Python :: 3.10
Classifier: Programming Language :: Python :: 3.11
Requires-Dist: Markdown (>=3.4.1,<4.0.0)
Requires-Dist: channels[daphne] (>=4.0.0,<5.0.0)
Requires-Dist: matrix-nio (>=0.20.0,<0.21.0)
Project-URL: Repository, https://github.com/nim65s/matrix-asgi.git
